rm_logger/__init__.py
rm_logger/rm_logger.py
rm_logger/rm_logger_test.py
rm_logger-0.0.1.dist-info/LICENSE
rm_logger-0.0.1.dist-info/METADATA
rm_logger-0.0.1.dist-info/WHEEL
rm_logger-0.0.1.dist-info/top_level.txt
rm_logger-0.0.1.dist-info/RECORD
