Metadata-Version: 2.1
Name: rm-logger
Version: 0.0.1
Summary: A generic logging class
Home-page: UNKNOWN
Author: Chris O'Brien
Author-email: christopher.obrien@remindermedia.com
License: UNKNOWN
Platform: UNKNOWN
Classifier: Programming Language :: Python :: 2
